glint4py/__init__.py
glint4py/app.py
glint4py/error_handler.py
glint4py/glint.py
glint4py/middleware.py
glint4py/request.py
glint4py/response.py
glint4py/router.py
glint4py/templates.py
glint4py-0.3.dist-info/LICENSE
glint4py-0.3.dist-info/METADATA
glint4py-0.3.dist-info/WHEEL
glint4py-0.3.dist-info/top_level.txt
glint4py-0.3.dist-info/RECORD
