Metadata-Version: 2.1
Name: glint4py
Version: 0.3
Summary: Glint is an open-source Python framework used to create lightweight, fast, and efficient server applications.
Home-page: https://github.com/acariustv/Glint
Author: acariustv-ufosproject
Author-email: acariustv@web.de
Classifier: Programming Language :: Python :: 3
Classifier: License :: OSI Approved :: MIT License
Classifier: Operating System :: OS Independent
Requires-Python: >=3.6
License-File: LICENSE
